OpenFintech/Data.py
OpenFintech/Model.py
OpenFintech/__init__.py
OpenFintech-0.2.2.dist-info/LICENSE
OpenFintech-0.2.2.dist-info/METADATA
OpenFintech-0.2.2.dist-info/WHEEL
OpenFintech-0.2.2.dist-info/top_level.txt
OpenFintech-0.2.2.dist-info/RECORD
