Metadata-Version: 2.1
Name: OpenFintech
Version: 0.2.2
Home-page: https://github.com/Laurier-Fintech/OpenFintech
Author: Laurier Fintech
Author-email: team@wlufintech.com
License-File: LICENSE
Requires-Dist: requests
Requires-Dist: pandas
Requires-Dist: python-dotenv
